{
  "uretim_zamani": "2026-05-12T20:26:16.394635+00:00",
  "haberler": [
    {
      "baslik": "Bambu Lab is abusing the open source social contract",
      "url": "https://www.jeffgeerling.com/blog/2026/bambu-lab-abusing-open-source-social-contract/",
      "kaynak": "HN",
      "skor": 883,
      "yas_saat": 5.5,
      "yorum_sayisi": 303
    },
    {
      "baslik": "Screenshots of Old Desktop OSes",
      "url": "http://www.typewritten.org/Media/",
      "kaynak": "HN",
      "skor": 594,
      "yas_saat": 15.2,
      "yorum_sayisi": 309
    },
    {
      "baslik": "They Live (1988) inspired Adblocker",
      "url": "https://github.com/davmlaw/they_live_adblocker",
      "kaynak": "HN",
      "skor": 519,
      "yas_saat": 19.8,
      "yorum_sayisi": 168
    }
  ]
}