{
  "uretim_zamani": "2026-05-03T15:27:11.575344+00:00",
  "haberler": [
    {
      "baslik": "VS Code inserting 'Co-Authored-by Copilot' into commits regardless of usage",
      "url": "https://github.com/microsoft/vscode/pull/310226",
      "kaynak": "HN",
      "skor": 1359,
      "yas_saat": 19.5,
      "yorum_sayisi": 732
    },
    {
      "baslik": "Dav2d",
      "url": "https://code.videolan.org/videolan/dav2d",
      "kaynak": "HN",
      "skor": 548,
      "yas_saat": 21.9,
      "yorum_sayisi": 155
    },
    {
      "baslik": "NetHack 5.0.0",
      "url": "https://nethack.org/v500/release.html",
      "kaynak": "HN",
      "skor": 478,
      "yas_saat": 21.4,
      "yorum_sayisi": 157
    }
  ]
}