{
  "uretim": "2026-06-28T17:25:10+00:00",
  "kanal": "TrendCatcher",
  "abone": 47,
  "toplam_video": 92,
  "toplam_izlenme_yaşam_boyu": 44261,
  "son_90g_izlenme": 42727,
  "son_14g_izlenme": 19239,
  "gunluk_izlenme_tahmin": 1374.2,
  "early_tier": {
    "abone_hedef": 500,
    "abone_yuzde": 9.4,
    "abone_kalan": 453,
    "shorts_hedef_90g": 3000000,
    "shorts_yuzde_90g": 1.42,
    "shorts_kalan_90g": 2957273,
    "tahmini_gun_shorts": 2152
  },
  "full_tier": {
    "abone_hedef": 1000,
    "abone_yuzde": 4.7,
    "abone_kalan": 953,
    "shorts_hedef_90g": 10000000,
    "shorts_yuzde_90g": 0.43,
    "shorts_kalan_90g": 9957273,
    "tahmini_gun_shorts": 7246
  }
}